ckanext_search_autocomplete-0.1.0-py3.10-nspkg.pth
ckanext/search_autocomplete/__init__.py
ckanext/search_autocomplete/helpers.py
ckanext/search_autocomplete/interfaces.py
ckanext/search_autocomplete/plugin.py
ckanext/search_autocomplete/utils.py
ckanext/search_autocomplete/assets/webassets.yml
ckanext/search_autocomplete/assets/css/search_autocomplete.css
ckanext/search_autocomplete/assets/js/search_autocomplete.js
ckanext/search_autocomplete/templates/base.html
ckanext/search_autocomplete/templates/snippets/search_form.html
ckanext/search_autocomplete/tests/__init__.py
ckanext/search_autocomplete/tests/test_plugin.py
ckanext/search_autocomplete/tests/logic/__init__.py
ckanext/search_autocomplete/tests/logic/test_action.py
ckanext_search_autocomplete-0.1.0.dist-info/LICENSE
ckanext_search_autocomplete-0.1.0.dist-info/METADATA
ckanext_search_autocomplete-0.1.0.dist-info/WHEEL
ckanext_search_autocomplete-0.1.0.dist-info/entry_points.txt
ckanext_search_autocomplete-0.1.0.dist-info/namespace_packages.txt
ckanext_search_autocomplete-0.1.0.dist-info/top_level.txt
ckanext_search_autocomplete-0.1.0.dist-info/RECORD
