Metadata-Version: 2.1
Name: ckanext-search-autocomplete
Version: 0.1.0
Summary: Search autocompletion
Home-page: https://github.com/mutantsan/ckanext-search-autocomplete
Author: Alexandr Cherniavskyi
Author-email: mutantsan@gmail.com
License: AGPL
Keywords: CKAN
Classifier: Development Status :: 4 - Beta
Classifier: License :: OSI Approved :: GNU Affero General Public License v3 or later (AGPLv3+)
Classifier: Programming Language :: Python :: 2.7
License-File: LICENSE
